tkyml/__init__.py
tkyml-0.0.3.dist-info/LICENSE
tkyml-0.0.3.dist-info/METADATA
tkyml-0.0.3.dist-info/WHEEL
tkyml-0.0.3.dist-info/top_level.txt
tkyml-0.0.3.dist-info/RECORD
