Metadata-Version: 2.1
Name: tkyml
Version: 0.0.3
Summary: A python implementation to separate declarative and functional code of a tkinter UI
Author-email: Lucas Maillet <loucas.maillet.pro@gmail.com>
Project-URL: Repository, https://github.com/LoucasMaillet/tkyml
Project-URL: Documentation, https://github.com/LoucasMaillet/tkyml/docs
Project-URL: Bug Tracker, https://github.com/LoucasMaillet/tkyml/issues
Classifier: Programming Language :: Python :: 3
Classifier: License :: OSI Approved :: MIT License
Classifier: Operating System :: OS Independent
Requires-Python: >=3.11
License-File: LICENSE
Requires-Dist: pyyaml (>=6.0)
Requires-Dist: pillow (>=9.3.0)
Requires-Dist: pywin32 (>=305)
Requires-Dist: tkextrafont (>=0.6.3)
